flask_mongokit.py
setup.py
Flask_MongoKit.egg-info/PKG-INFO
Flask_MongoKit.egg-info/SOURCES.txt
Flask_MongoKit.egg-info/dependency_links.txt
Flask_MongoKit.egg-info/not-zip-safe
Flask_MongoKit.egg-info/requires.txt
Flask_MongoKit.egg-info/top_level.txt