Metadata-Version: 1.0
Name: Flask-MongoKit
Version: 0.4
Summary: A Flask extension simplifies to use MongoKit
Home-page: http://github.com/jarus/flask-mongokit
Author: Christoph Heer
Author-email: Christoph.Heer@googlemail.com
License: BSD
Platform: any
Classifier: Development Status :: 4 - Beta
Classifier: Environment :: Web Environment
Classifier: Intended Audience :: Developers
Classifier: License :: OSI Approved :: BSD License
Classifier: Operating System :: OS Independent
Classifier: Programming Language :: Python
Classifier: Topic :: Internet :: WWW/HTTP :: Dynamic Content
Classifier: Topic :: Software Development :: Libraries :: Python Modules
